{
  "NTProvider": {
    "types": {
      "/FMSInfo": "FMSInfo",
      "/SmartDashboard/Robot/Auto/Command": "String Chooser",
      "/SmartDashboard/Robot/Drive/Orientation": "String Chooser",
      "/SmartDashboard/Robot/Drive/SpeedMode": "String Chooser"
    }
  },
  "NetworkTables": {
    "transitory": {
      "FMSInfo": {
        "open": true
      },
      "SmartDashboard": {
        "Robot": {
          "Auto": {
            "Command": {
              "open": true,
              "string[]##v_/SmartDashboard/Robot/Auto/Command/options": {
                "open": true
              }
            },
            "open": true
          },
          "Battery": {
            "open": true
          }
        },
        "Timing": {
          "open": true
        },
        "open": true
      }
    }
  },
  "NetworkTables Info": {
    "visible": true
  }
}
